{
  "campaign": {
    "id": "HOOK-002",
    "week": 1,
    "day": 5,
    "type": "Hook",
    "title": "Post Your Event",
    "subject": "Got an event coming up? Post it free to 10,000+ locals",
    "landing_page": "post-your-event",
    "template": "event-posting",
    "description": "Show SMB a sample event for their business and invite them to post it"
  },
  "landing_page": {
    "campaign_id": "HOOK-002",
    "landing_page_slug": "post-your-event",
    "url": "/events/new/your-business",
    "template_id": "event-posting",
    "template_name": "Event Posting",
    "slide_count": 5,
    "duration_seconds": 90,
    "primary_cta": "post_event",
    "secondary_cta": "customize_event",
    "ai_persona": "Sarah",
    "ai_tone": "Excited, encouraging",
    "ai_goal": "Get user to post their first event",
    "data_capture_fields": "name, email, business_name, event_type",
    "audio_base_url": "https://cdn.fibonacco.com/presentations/post-your-event/audio/",
    "crm_tracking": true,
    "conversion_goal": "event_posted",
    "utm_source": "email",
    "utm_medium": "outbound",
    "utm_campaign": "90day-week1-hook",
    "utm_content": "HOOK-002"
  },
  "template": {
    "template_id": "event-posting",
    "name": "Quick Action",
    "slides": 5,
    "duration": 115,
    "purpose": "hook",
    "audio_required": true
  },
  "slides": [
    {
      "slide_num": 1,
      "component": "PersonalizedHeroSlide",
      "title": "Your Event Could Reach Thousands",
      "content": {
        "headline": "your business, Got an Event Coming Up?",
        "subhead": "Post it free to 10,000+ people in your city",
        "visual": "Event calendar with featured events",
        "stats": {
          "audience": "10,000",
          "avg_views": "800",
          "engagement": "high"
        }
      },
      "narration": "Hey there, quick question: do you have any events coming up at your business? A sale, a workshop, a special, an open house\u2014anything? Because our events calendar reaches over 10,000 people in your city. And posting is completely free.",
      "duration_seconds": 20,
      "audio_file": "slide-01-hero.mp3"
    },
    {
      "slide_num": 2,
      "component": "EventPreviewSlide",
      "title": "We Drafted One For You",
      "content": {
        "headline": "We Created a Sample Event",
        "event_preview": {
          "title": "Community Open House",
          "date": "This Saturday",
          "time": "10:00 AM - 2:00 PM",
          "description": "Join us for a special community event",
          "image": "placeholder_event_image",
          "status": "Draft - Ready to Post"
        },
        "note": "This is just a suggestion based on your business type. Edit it however you want."
      },
      "narration": "We actually went ahead and drafted a sample event for you. Based on what local businesses typically do, we suggested: Community Open House. This is just a starting point\u2014you can edit the title, date, description, everything. Or create something completely different.",
      "duration_seconds": 25,
      "audio_file": "slide-02-preview.mp3"
    },
    {
      "slide_num": 3,
      "component": "BenefitsSlide",
      "title": "Why Events Work",
      "content": {
        "headline": "Events Get Results",
        "benefits": [
          {
            "stat": "800",
            "label": "average views per event"
          },
          {
            "stat": "45",
            "label": "people save events to attend"
          },
          {
            "stat": "25",
            "label": "shares to friends and family"
          },
          {
            "stat": "Free",
            "label": "to post, always"
          }
        ],
        "testimonial": {
          "quote": "Posted a workshop, got 40 RSVPs. Best marketing I've ever done.",
          "author": "Local Business Owner",
          "business_type": "Local Business"
        }
      },
      "narration": "Here's why events work so well. On average, events on our calendar get 800 views. 45 people typically save an event to attend later. And events get shared\u201425 shares on average to friends and family. One business owner told us: 'Posted a workshop, got 40 RSVPs. Best marketing I've ever done.' And it's completely free to post.",
      "duration_seconds": 25,
      "audio_file": "slide-03-benefits.mp3"
    },
    {
      "slide_num": 4,
      "component": "IdeaSlide",
      "title": "Event Ideas For You",
      "content": {
        "headline": "Event Ideas for local Businesses",
        "ideas": [
          {
            "idea": "Customer Appreciation Day",
            "example": "a thank-you event with refreshments and special offers"
          },
          {
            "idea": "Workshop or Demo",
            "example": "a hands-on session showcasing your expertise"
          },
          {
            "idea": "Seasonal Sale Event",
            "example": "a limited-time promotion tied to the season"
          },
          {
            "idea": "Community Partnership Event",
            "example": "team up with neighboring businesses for a block event"
          }
        ],
        "note": "Don't overthink it. Even 'Now Booking Appointments' counts as news."
      },
      "narration": "Not sure what to post? Here are ideas that work great for local businesses. Customer Appreciation Day\u2014like a thank-you event with refreshments and special offers. Workshop or Demo. Seasonal Sale Event. Or Community Partnership Event. Don't overthink it. Even something simple like 'Now Booking Appointments for Spring' gives people a reason to engage.",
      "duration_seconds": 25,
      "audio_file": "slide-04-ideas.mp3"
    },
    {
      "slide_num": 5,
      "component": "CTASlide",
      "title": "Post Your Event",
      "content": {
        "headline": "Ready to Reach 10,000+ People?",
        "cta_primary": {
          "label": "Post This Event",
          "action": "post_event",
          "description": "Use our suggested event (edit anytime)"
        },
        "cta_secondary": {
          "label": "Create My Own Event",
          "action": "create_custom_event",
          "description": "Start fresh with your own idea"
        },
        "trust": "Free forever \u2022 Edit anytime \u2022 Cancel anytime",
        "urgency": "Events posted this week get featured in our newsletter"
      },
      "narration": "Ready to reach 10,000 people in your city? Click 'Post This Event' to use the one we drafted\u2014you can edit it anytime. Or click 'Create My Own' to start fresh with your own idea. Either way, it's free, you can edit anytime, and events posted this week get featured in our newsletter. Let's get people to your next event.",
      "duration_seconds": 20,
      "audio_file": "slide-05-cta.mp3"
    }
  ],
  "connections": {
    "leads_to": [
      "HOWTO-003"
    ],
    "follows": "HOOK-001",
    "related": [
      "HOOK-003",
      "HOOK-004"
    ]
  }
}